{
  "name": "Genesis 12", 
  "abbrev": "Gen. 12", 
  "number": "12", 
  "churchUri": "/scriptures/ot/gen/12", 
  "paragraphs": [
    {
      "type": "chapter-title", 
      "id": "ct1", 
      "content": "Chapter 12", 
      "contentHtml": "Chapter 12", 
      "number": null, 
      "pageNumber": "17", 
      "compareId": "genesis-12_ct1", 
      "churchId": "title_number1"
    }, 
    {
      "type": "verse", 
      "id": "v1", 
      "content": "Now the LORD had said unto Abram, Get thee out of thy country, and from thy kindred, and from thy father’s house, unto a land that I will shew thee:", 
      "contentHtml": "Now the <span class=\"small-caps\">Lord</span> had said unto Abram, Get thee out of thy country, and from thy kindred, and from thy father’s house, unto a land that I will shew thee:", 
      "number": "1", 
      "pageNumber": "17", 
      "compareId": "genesis-12_v1", 
      "churchId": "p1"
    }, 
    {
      "type": "verse", 
      "id": "v2", 
      "content": "And I will make of thee a great nation, and I will bless thee, and make thy name great; and thou shalt be a blessing:", 
      "contentHtml": "And I will make of thee a great nation, and I will bless thee, and make thy name great; and thou shalt be a blessing:", 
      "number": "2", 
      "pageNumber": "17", 
      "compareId": "genesis-12_v2", 
      "churchId": "p2"
    }, 
    {
      "type": "verse", 
      "id": "v3", 
      "content": "And I will bless them that bless thee, and curse him that curseth thee: and in thee shall all families of the earth be blessed.", 
      "contentHtml": "And I will bless them that bless thee, and curse him that curseth thee: and in thee shall all families of the earth be blessed.", 
      "number": "3", 
      "pageNumber": "17", 
      "compareId": "genesis-12_v3", 
      "churchId": "p3"
    }, 
    {
      "type": "verse", 
      "id": "v4", 
      "content": "So Abram departed, as the LORD had spoken unto him; and Lot went with him: and Abram was seventy and five years old when he departed out of Haran.", 
      "contentHtml": "So Abram departed, as the <span class=\"small-caps\">Lord</span> had spoken unto him; and Lot went with him: and Abram <span class=\"clarity-word\">was</span> seventy and five years old when he departed out of Haran.", 
      "number": "4", 
      "pageNumber": "17", 
      "compareId": "genesis-12_v4", 
      "churchId": "p4"
    }, 
    {
      "type": "verse", 
      "id": "v5", 
      "content": "And Abram took Sarai his wife, and Lot his brother’s son, and all their substance that they had gathered, and the souls that they had gotten in Haran; and they went forth to go into the land of Canaan; and into the land of Canaan they came.", 
      "contentHtml": "And Abram took Sarai his wife, and Lot his brother’s son, and all their substance that they had gathered, and the souls that they had gotten in Haran; and they went forth to go into the land of Canaan; and into the land of Canaan they came.", 
      "number": "5", 
      "pageNumber": "17", 
      "compareId": "genesis-12_v5", 
      "churchId": "p5"
    }, 
    {
      "type": "verse", 
      "id": "v6", 
      "content": "¶ And Abram passed through the land unto the place of Sichem, unto the plain of Moreh. And the Canaanite was then in the land.", 
      "contentHtml": "¶ And Abram passed through the land unto the place of Sichem, unto the plain of Moreh. And the Canaanite <span class=\"clarity-word\">was</span> then in the land.", 
      "number": "6", 
      "pageNumber": "17", 
      "compareId": "genesis-12_v6", 
      "churchId": "p6"
    }, 
    {
      "type": "verse", 
      "id": "v7", 
      "content": "And the LORD appeared unto Abram, and said, Unto thy seed will I give this land: and there builded he an altar unto the LORD, who appeared unto him.", 
      "contentHtml": "And the <span class=\"small-caps\">Lord</span> appeared unto Abram, and said, Unto thy seed will I give this land: and there builded he an altar unto the <span class=\"small-caps\">Lord</span>, who appeared unto him.", 
      "number": "7", 
      "pageNumber": "17", 
      "compareId": "genesis-12_v7", 
      "churchId": "p7"
    }, 
    {
      "type": "verse", 
      "id": "v8", 
      "content": "And he removed from thence unto a mountain on the east of Beth-el, and pitched his tent, having Beth-el on the west, and Hai on the east: and there he builded an altar unto the LORD, and called upon the name of the LORD.", 
      "contentHtml": "And he removed from thence unto a mountain on the east of Beth-el, and pitched his tent, <span class=\"clarity-word\">having</span> Beth-el on the west, and Hai on the east: and there he builded an altar unto the <span class=\"small-caps\">Lord</span>, and called upon the name of the <span class=\"small-caps\">Lord</span>.", 
      "number": "8", 
      "pageNumber": "17", 
      "compareId": "genesis-12_v8", 
      "churchId": "p8"
    }, 
    {
      "type": "verse", 
      "id": "v9", 
      "content": "And Abram journeyed, going on still toward the south.", 
      "contentHtml": "And Abram journeyed, going on still toward the south.", 
      "number": "9", 
      "pageNumber": "17", 
      "compareId": "genesis-12_v9", 
      "churchId": "p9"
    }, 
    {
      "type": "verse", 
      "id": "v10", 
      "content": "¶ And there was a famine in the land: and Abram went down into Egypt to sojourn there; for the famine was grievous in the land.", 
      "contentHtml": "¶ And there was a famine in the land: and Abram went down into Egypt to sojourn there; for the famine <span class=\"clarity-word\">was</span> grievous in the land.", 
      "number": "10", 
      "pageNumber": "17", 
      "compareId": "genesis-12_v10", 
      "churchId": "p10"
    }, 
    {
      "type": "verse", 
      "id": "v11", 
      "content": "And it came to pass, when he was come near to enter into Egypt, that he said unto Sarai his wife, Behold now, I know that thou art a fair woman to look upon:", 
      "contentHtml": "And it came to pass, when he was come near to enter into Egypt, that he said unto Sarai his wife, Behold now, I know that thou <span class=\"clarity-word\">art</span> a fair woman to look upon:", 
      "number": "11", 
      "pageNumber": "17", 
      "compareId": "genesis-12_v11", 
      "churchId": "p11"
    }, 
    {
      "type": "verse", 
      "id": "v12", 
      "content": "Therefore it shall come to pass, when the Egyptians shall see thee, that they shall say, This is his wife: and they will kill me, but they will save thee alive.", 
      "contentHtml": "Therefore it shall come to pass, when the Egyptians shall see thee, that they shall say, This <span class=\"clarity-word\">is</span> his wife: and they will kill me, but they will save thee alive.", 
      "number": "12", 
      "pageNumber": "17,18", 
      "compareId": "genesis-12_v12", 
      "churchId": "p12"
    }, 
    {
      "type": "verse", 
      "id": "v13", 
      "content": "Say, I pray thee, thou art my sister: that it may be well with me for thy sake; and my soul shall live because of thee.", 
      "contentHtml": "Say, I pray thee, thou <span class=\"clarity-word\">art</span> my sister: that it may be well with me for thy sake; and my soul shall live because of thee.", 
      "number": "13", 
      "pageNumber": "18", 
      "compareId": "genesis-12_v13", 
      "churchId": "p13"
    }, 
    {
      "type": "verse", 
      "id": "v14", 
      "content": "¶ And it came to pass, that, when Abram was come into Egypt, the Egyptians beheld the woman that she was very fair.", 
      "contentHtml": "¶ And it came to pass, that, when Abram was come into Egypt, the Egyptians beheld the woman that she <span class=\"clarity-word\">was</span> very fair.", 
      "number": "14", 
      "pageNumber": "18", 
      "compareId": "genesis-12_v14", 
      "churchId": "p14"
    }, 
    {
      "type": "verse", 
      "id": "v15", 
      "content": "The princes also of Pharaoh saw her, and commended her before Pharaoh: and the woman was taken into Pharaoh’s house.", 
      "contentHtml": "The princes also of Pharaoh saw her, and commended her before Pharaoh: and the woman was taken into Pharaoh’s house.", 
      "number": "15", 
      "pageNumber": "18", 
      "compareId": "genesis-12_v15", 
      "churchId": "p15"
    }, 
    {
      "type": "verse", 
      "id": "v16", 
      "content": "And he entreated Abram well for her sake: and he had sheep, and oxen, and he asses, and menservants, and maidservants, and she asses, and camels.", 
      "contentHtml": "And he entreated Abram well for her sake: and he had sheep, and oxen, and he asses, and menservants, and maidservants, and she asses, and camels.", 
      "number": "16", 
      "pageNumber": "18", 
      "compareId": "genesis-12_v16", 
      "churchId": "p16"
    }, 
    {
      "type": "verse", 
      "id": "v17", 
      "content": "And the LORD plagued Pharaoh and his house with great plagues because of Sarai Abram’s wife.", 
      "contentHtml": "And the <span class=\"small-caps\">Lord</span> plagued Pharaoh and his house with great plagues because of Sarai Abram’s wife.", 
      "number": "17", 
      "pageNumber": "18", 
      "compareId": "genesis-12_v17", 
      "churchId": "p17"
    }, 
    {
      "type": "verse", 
      "id": "v18", 
      "content": "And Pharaoh called Abram, and said, What is this that thou hast done unto me? why didst thou not tell me that she was thy wife?", 
      "contentHtml": "And Pharaoh called Abram, and said, What <span class=\"clarity-word\">is</span> this <span class=\"clarity-word\">that</span> thou hast done unto me? why didst thou not tell me that she <span class=\"clarity-word\">was</span> thy wife?", 
      "number": "18", 
      "pageNumber": "18", 
      "compareId": "genesis-12_v18", 
      "churchId": "p18"
    }, 
    {
      "type": "verse", 
      "id": "v19", 
      "content": "Why saidst thou, She is my sister? so I might have taken her to me to wife: now therefore behold thy wife, take her, and go thy way.", 
      "contentHtml": "Why saidst thou, She <span class=\"clarity-word\">is</span> my sister? so I might have taken her to me to wife: now therefore behold thy wife, take <span class=\"clarity-word\">her,</span> and go thy way.", 
      "number": "19", 
      "pageNumber": "18", 
      "compareId": "genesis-12_v19", 
      "churchId": "p19"
    }, 
    {
      "type": "verse", 
      "id": "v20", 
      "content": "And Pharaoh commanded his men concerning him: and they sent him away, and his wife, and all that he had.", 
      "contentHtml": "And Pharaoh commanded <span class=\"clarity-word\">his</span> men concerning him: and they sent him away, and his wife, and all that he had.", 
      "number": "20", 
      "pageNumber": "18", 
      "compareId": "genesis-12_v20", 
      "churchId": "p20"
    }
  ], 
  "media": [
    {
      "type": "audio", 
      "subtype": "spoken-female", 
      "url": "https://media2.ldscdn.org/assets/scriptures/the-old-testament/2015-11-0120-genesis-12-female-voice-64k-eng.mp3", 
      "imageUrl": null, 
      "startSeconds": null, 
      "endSeconds": null, 
      "source": "ChurchofJesusChrist.org", 
      "churchAssetId": null, 
      "churchImageAssetId": null
    }, 
    {
      "type": "audio", 
      "subtype": "spoken-male", 
      "url": "https://media2.ldscdn.org/assets/scriptures/the-old-testament/2015-11-0120-genesis-12-male-voice-64k-eng.mp3", 
      "imageUrl": null, 
      "startSeconds": null, 
      "endSeconds": null, 
      "source": "ChurchofJesusChrist.org", 
      "churchAssetId": null, 
      "churchImageAssetId": null
    }
  ]
}