{
  "name": "Jeremiah 42", 
  "abbrev": "Jer. 42", 
  "number": "42", 
  "churchUri": "/scriptures/ot/jer/42", 
  "paragraphs": [
    {
      "type": "chapter-title", 
      "id": "ct1", 
      "content": "Chapter 42", 
      "contentHtml": "Chapter 42", 
      "number": null, 
      "pageNumber": "1001", 
      "compareId": "jeremiah-42_ct1", 
      "churchId": "title_number1"
    }, 
    {
      "type": "verse", 
      "id": "v1", 
      "content": "Then all the captains of the forces, and Johanan the son of Kareah, and Jezaniah the son of Hoshaiah, and all the people from the least even unto the greatest, came near,", 
      "contentHtml": "Then all the captains of the forces, and Johanan the son of Kareah, and Jezaniah the son of Hoshaiah, and all the people from the least even unto the greatest, came near,", 
      "number": "1", 
      "pageNumber": "1001", 
      "compareId": "jeremiah-42_v1", 
      "churchId": "p1"
    }, 
    {
      "type": "verse", 
      "id": "v2", 
      "content": "And said unto Jeremiah the prophet, Let, we beseech thee, our supplication be accepted before thee, and pray for us unto the LORD thy God, even for all this remnant; (for we are left but a few of many, as thine eyes do behold us:)", 
      "contentHtml": "And said unto Jeremiah the prophet, Let, we beseech thee, our supplication be accepted before thee, and pray for us unto the <span class=\"small-caps\">Lord</span> thy God, <span class=\"clarity-word\">even</span> for all this remnant; (for we are left <span class=\"clarity-word\">but</span> a few of many, as thine eyes do behold us:)", 
      "number": "2", 
      "pageNumber": "1001", 
      "compareId": "jeremiah-42_v2", 
      "churchId": "p2"
    }, 
    {
      "type": "verse", 
      "id": "v3", 
      "content": "That the LORD thy God may shew us the way wherein we may walk, and the thing that we may do.", 
      "contentHtml": "That the <span class=\"small-caps\">Lord</span> thy God may shew us the way wherein we may walk, and the thing that we may do.", 
      "number": "3", 
      "pageNumber": "1001", 
      "compareId": "jeremiah-42_v3", 
      "churchId": "p3"
    }, 
    {
      "type": "verse", 
      "id": "v4", 
      "content": "Then Jeremiah the prophet said unto them, I have heard you; behold, I will pray unto the LORD your God according to your words; and it shall come to pass, that whatsoever thing the LORD shall answer you, I will declare it unto you; I will keep nothing back from you.", 
      "contentHtml": "Then Jeremiah the prophet said unto them, I have heard <span class=\"clarity-word\">you;</span> behold, I will pray unto the <span class=\"small-caps\">Lord</span> your God according to your words; and it shall come to pass, <span class=\"clarity-word\">that</span> whatsoever thing the <span class=\"small-caps\">Lord</span> shall answer you, I will declare <span class=\"clarity-word\">it</span> unto you; I will keep nothing back from you.", 
      "number": "4", 
      "pageNumber": "1001", 
      "compareId": "jeremiah-42_v4", 
      "churchId": "p4"
    }, 
    {
      "type": "verse", 
      "id": "v5", 
      "content": "Then they said to Jeremiah, The LORD be a true and faithful witness between us, if we do not even according to all things for the which the LORD thy God shall send thee to us.", 
      "contentHtml": "Then they said to Jeremiah, The <span class=\"small-caps\">Lord</span> be a true and faithful witness between us, if we do not even according to all things for the which the <span class=\"small-caps\">Lord</span> thy God shall send thee to us.", 
      "number": "5", 
      "pageNumber": "1001", 
      "compareId": "jeremiah-42_v5", 
      "churchId": "p5"
    }, 
    {
      "type": "verse", 
      "id": "v6", 
      "content": "Whether it be good, or whether it be evil, we will obey the voice of the LORD our God, to whom we send thee; that it may be well with us, when we obey the voice of the LORD our God.", 
      "contentHtml": "Whether <span class=\"clarity-word\">it be</span> good, or whether <span class=\"clarity-word\">it be</span> evil, we will obey the voice of the <span class=\"small-caps\">Lord</span> our God, to whom we send thee; that it may be well with us, when we obey the voice of the <span class=\"small-caps\">Lord</span> our God.", 
      "number": "6", 
      "pageNumber": "1001", 
      "compareId": "jeremiah-42_v6", 
      "churchId": "p6"
    }, 
    {
      "type": "verse", 
      "id": "v7", 
      "content": "¶ And it came to pass after ten days, that the word of the LORD came unto Jeremiah.", 
      "contentHtml": "¶ And it came to pass after ten days, that the word of the <span class=\"small-caps\">Lord</span> came unto Jeremiah.", 
      "number": "7", 
      "pageNumber": "1001", 
      "compareId": "jeremiah-42_v7", 
      "churchId": "p7"
    }, 
    {
      "type": "verse", 
      "id": "v8", 
      "content": "Then called he Johanan the son of Kareah, and all the captains of the forces which were with him, and all the people from the least even to the greatest,", 
      "contentHtml": "Then called he Johanan the son of Kareah, and all the captains of the forces which <span class=\"clarity-word\">were</span> with him, and all the people from the least even to the greatest,", 
      "number": "8", 
      "pageNumber": "1001", 
      "compareId": "jeremiah-42_v8", 
      "churchId": "p8"
    }, 
    {
      "type": "verse", 
      "id": "v9", 
      "content": "And said unto them, Thus saith the LORD, the God of Israel, unto whom ye sent me to present your supplication before him;", 
      "contentHtml": "And said unto them, Thus saith the <span class=\"small-caps\">Lord</span>, the God of Israel, unto whom ye sent me to present your supplication before him;", 
      "number": "9", 
      "pageNumber": "1001", 
      "compareId": "jeremiah-42_v9", 
      "churchId": "p9"
    }, 
    {
      "type": "verse", 
      "id": "v10", 
      "content": "If ye will still abide in this land, then will I build you, and not pull you down, and I will plant you, and not pluck you up: for I repent me of the evil that I have done unto you.", 
      "contentHtml": "If ye will still abide in this land, then will I build you, and not pull <span class=\"clarity-word\">you</span> down, and I will plant you, and not pluck <span class=\"clarity-word\">you</span> up: for I repent me of the evil that I have done unto you.", 
      "number": "10", 
      "pageNumber": "1001", 
      "compareId": "jeremiah-42_v10", 
      "churchId": "p10"
    }, 
    {
      "type": "verse", 
      "id": "v11", 
      "content": "Be not afraid of the king of Babylon, of whom ye are afraid; be not afraid of him, saith the LORD: for I am with you to save you, and to deliver you from his hand.", 
      "contentHtml": "Be not afraid of the king of Babylon, of whom ye are afraid; be not afraid of him, saith the <span class=\"small-caps\">Lord</span>: for I <span class=\"clarity-word\">am</span> with you to save you, and to deliver you from his hand.", 
      "number": "11", 
      "pageNumber": "1001", 
      "compareId": "jeremiah-42_v11", 
      "churchId": "p11"
    }, 
    {
      "type": "verse", 
      "id": "v12", 
      "content": "And I will shew mercies unto you, that he may have mercy upon you, and cause you to return to your own land.", 
      "contentHtml": "And I will shew mercies unto you, that he may have mercy upon you, and cause you to return to your own land.", 
      "number": "12", 
      "pageNumber": "1001,1002", 
      "compareId": "jeremiah-42_v12", 
      "churchId": "p12"
    }, 
    {
      "type": "verse", 
      "id": "v13", 
      "content": "¶ But if ye say, We will not dwell in this land, neither obey the voice of the LORD your God,", 
      "contentHtml": "¶ But if ye say, We will not dwell in this land, neither obey the voice of the <span class=\"small-caps\">Lord</span> your God,", 
      "number": "13", 
      "pageNumber": "1002", 
      "compareId": "jeremiah-42_v13", 
      "churchId": "p13"
    }, 
    {
      "type": "verse", 
      "id": "v14", 
      "content": "Saying, No; but we will go into the land of Egypt, where we shall see no war, nor hear the sound of the trumpet, nor have hunger of bread; and there will we dwell:", 
      "contentHtml": "Saying, No; but we will go into the land of Egypt, where we shall see no war, nor hear the sound of the trumpet, nor have hunger of bread; and there will we dwell:", 
      "number": "14", 
      "pageNumber": "1002", 
      "compareId": "jeremiah-42_v14", 
      "churchId": "p14"
    }, 
    {
      "type": "verse", 
      "id": "v15", 
      "content": "And now therefore hear the word of the LORD, ye remnant of Judah; Thus saith the LORD of hosts, the God of Israel; If ye wholly set your faces to enter into Egypt, and go to sojourn there;", 
      "contentHtml": "And now therefore hear the word of the <span class=\"small-caps\">Lord</span>, ye remnant of Judah; Thus saith the <span class=\"small-caps\">Lord</span> of hosts, the God of Israel; If ye wholly set your faces to enter into Egypt, and go to sojourn there;", 
      "number": "15", 
      "pageNumber": "1002", 
      "compareId": "jeremiah-42_v15", 
      "churchId": "p15"
    }, 
    {
      "type": "verse", 
      "id": "v16", 
      "content": "Then it shall come to pass, that the sword, which ye feared, shall overtake you there in the land of Egypt, and the famine, whereof ye were afraid, shall follow close after you there in Egypt; and there ye shall die.", 
      "contentHtml": "Then it shall come to pass, <span class=\"clarity-word\">that</span> the sword, which ye feared, shall overtake you there in the land of Egypt, and the famine, whereof ye were afraid, shall follow close after you there in Egypt; and there ye shall die.", 
      "number": "16", 
      "pageNumber": "1002", 
      "compareId": "jeremiah-42_v16", 
      "churchId": "p16"
    }, 
    {
      "type": "verse", 
      "id": "v17", 
      "content": "So shall it be with all the men that set their faces to go into Egypt to sojourn there; they shall die by the sword, by the famine, and by the pestilence: and none of them shall remain or escape from the evil that I will bring upon them.", 
      "contentHtml": "So shall it be with all the men that set their faces to go into Egypt to sojourn there; they shall die by the sword, by the famine, and by the pestilence: and none of them shall remain or escape from the evil that I will bring upon them.", 
      "number": "17", 
      "pageNumber": "1002", 
      "compareId": "jeremiah-42_v17", 
      "churchId": "p17"
    }, 
    {
      "type": "verse", 
      "id": "v18", 
      "content": "For thus saith the LORD of hosts, the God of Israel; As mine anger and my fury hath been poured forth upon the inhabitants of Jerusalem; so shall my fury be poured forth upon you, when ye shall enter into Egypt: and ye shall be an execration, and an astonishment, and a curse, and a reproach; and ye shall see this place no more.", 
      "contentHtml": "For thus saith the <span class=\"small-caps\">Lord</span> of hosts, the God of Israel; As mine anger and my fury hath been poured forth upon the inhabitants of Jerusalem; so shall my fury be poured forth upon you, when ye shall enter into Egypt: and ye shall be an execration, and an astonishment, and a curse, and a reproach; and ye shall see this place no more.", 
      "number": "18", 
      "pageNumber": "1002", 
      "compareId": "jeremiah-42_v18", 
      "churchId": "p18"
    }, 
    {
      "type": "verse", 
      "id": "v19", 
      "content": "¶ The LORD hath said concerning you, O ye remnant of Judah; Go ye not into Egypt: know certainly that I have admonished you this day.", 
      "contentHtml": "¶ The <span class=\"small-caps\">Lord</span> hath said concerning you, O ye remnant of Judah; Go ye not into Egypt: know certainly that I have admonished you this day.", 
      "number": "19", 
      "pageNumber": "1002", 
      "compareId": "jeremiah-42_v19", 
      "churchId": "p19"
    }, 
    {
      "type": "verse", 
      "id": "v20", 
      "content": "For ye dissembled in your hearts, when ye sent me unto the LORD your God, saying, Pray for us unto the LORD our God; and according unto all that the LORD our God shall say, so declare unto us, and we will do it.", 
      "contentHtml": "For ye dissembled in your hearts, when ye sent me unto the <span class=\"small-caps\">Lord</span> your God, saying, Pray for us unto the <span class=\"small-caps\">Lord</span> our God; and according unto all that the <span class=\"small-caps\">Lord</span> our God shall say, so declare unto us, and we will do <span class=\"clarity-word\">it.</span>", 
      "number": "20", 
      "pageNumber": "1002", 
      "compareId": "jeremiah-42_v20", 
      "churchId": "p20"
    }, 
    {
      "type": "verse", 
      "id": "v21", 
      "content": "And now I have this day declared it to you; but ye have not obeyed the voice of the LORD your God, nor any thing for the which he hath sent me unto you.", 
      "contentHtml": "And <span class=\"clarity-word\">now</span> I have this day declared <span class=\"clarity-word\">it</span> to you; but ye have not obeyed the voice of the <span class=\"small-caps\">Lord</span> your God, nor any <span class=\"clarity-word\">thing</span> for the which he hath sent me unto you.", 
      "number": "21", 
      "pageNumber": "1002", 
      "compareId": "jeremiah-42_v21", 
      "churchId": "p21"
    }, 
    {
      "type": "verse", 
      "id": "v22", 
      "content": "Now therefore know certainly that ye shall die by the sword, by the famine, and by the pestilence, in the place whither ye desire to go and to sojourn.", 
      "contentHtml": "Now therefore know certainly that ye shall die by the sword, by the famine, and by the pestilence, in the place whither ye desire to go <span class=\"clarity-word\">and</span> to sojourn.", 
      "number": "22", 
      "pageNumber": "1002", 
      "compareId": "jeremiah-42_v22", 
      "churchId": "p22"
    }
  ], 
  "media": [
    {
      "type": "audio", 
      "subtype": "spoken-female", 
      "url": "https://media2.ldscdn.org/assets/scriptures/the-old-testament/2015-11-7870-jeremiah-42-female-voice-64k-eng.mp3", 
      "imageUrl": null, 
      "startSeconds": null, 
      "endSeconds": null, 
      "source": "ChurchofJesusChrist.org", 
      "churchAssetId": null, 
      "churchImageAssetId": null
    }, 
    {
      "type": "audio", 
      "subtype": "spoken-male", 
      "url": "https://media2.ldscdn.org/assets/scriptures/the-old-testament/2015-11-7870-jeremiah-42-male-voice-64k-eng.mp3", 
      "imageUrl": null, 
      "startSeconds": null, 
      "endSeconds": null, 
      "source": "ChurchofJesusChrist.org", 
      "churchAssetId": null, 
      "churchImageAssetId": null
    }
  ]
}